<?xml version="1.0" encoding="UTF-8"?>
<Products>
		<Product>
			<ProductCode>K01.W-01.00343</ProductCode>
			<ProductName><![CDATA[WEB W 0208 34G UNISEX GÜNEŞ GÖZLÜĞÜ]]></ProductName>
			<Quantity>20</Quantity>
			<Price>643.63</Price>
			<Currency>TL</Currency>
			<TaxRate>18</TaxRate>
			<Barcode>8698716934614</Barcode>
			<Category>Güneş Gözlükleri>UNISEX GÜNEŞ GÖZLÜĞÜ</Category>
			<Description><![CDATA[<p><span><strong>Web</strong> Marka Güneş Gözlükleri Her Türlü FABRİKASYON Hatalara Karşı 2 Yıl Garantilidir.<br>Filiz Aksesuar Firması <strong>Web</strong> Markasının Yetkili Satıcı Belgesine Sahiptir.<br>Ürünlerin Tamamı Orijinal Olmakla Birlikte Orijinal Kılıfı Silme bezi ve Garanti Belgesi ile Gönderim Yapılmaktadır.<br>Şiparişleriniz Fatura ile Gönderim Yapıldığından Hediye Paketi Yapılamamaktadır.<br>Ürünlerin Tamamı Tek Ekartmandır. <br>Aynı modelin Farklı Ekartmanları Bulunmamaktadır. <br><strong>Web</strong> Marka <strong>W 0208 34G Model Gözlüğün</strong><br>Çerçeve Tipi .: <b>PİLOT METAL</b> Çerçevedir. <br>Çerçeve Rengi .: <b>ALTIN</b> Renkdir. <br>Cam Özelliği .: <b>ORGANİK KAHVERENGİ UV400 </b> Korumadır. <br>Gözlük bedeni olmadığında veya beğenmediğiniz zaman kullanmadığınız takdirde 7 iş günü içinde İade edebilirsiniz.<br>Site üzerinden iade kodu alıp tarafımıza göndermeniz gerekmektedir. <br>geri gönderim yaparken paketi size geldiği şekilde (Kılıfı, Silme Bezi, Garanti Belgesi ve Faturası ile) göndermeye dikkat etmelisiniz.<table><tr><th>Özellik Adı</th><th>Özellik Değeri</th></tr><tr><td style="text-align:right"><STRONG>Tipi .:</STRONG></td><td>PİLOT</td></tr><tr><td style="text-align:right"><STRONG>Gövde.:</STRONG></td><td>METAL</td></tr><tr><td style="text-align:right"><STRONG>Gövde Rengi.:</STRONG></td><td>ALTIN</td></tr><tr><td style="text-align:right"><STRONG>Ekartman.:</STRONG></td><td>59</td></tr><tr><td style="text-align:right"><STRONG>Burun Aralığı.:</STRONG></td><td>16</td></tr><tr><td style="text-align:right"><STRONG>Sap Uzunluğu.:</STRONG></td><td>145</td></tr><tr><td style="text-align:right"><STRONG>Çerçeve Özellik.:</STRONG></td><td></td></tr><tr><td style="text-align:right"><STRONG>.:</STRONG></td><td></td></tr><tr><td style="text-align:right"><STRONG>Cam Tasarımı.:</STRONG></td><td>DAMLA</td></tr><tr><td style="text-align:right"><STRONG>Cam Türü.:</STRONG></td><td>ORGANİK</td></tr><tr><td style="text-align:right"><STRONG>Cam Özellik.:</STRONG></td><td>AYNALI</td></tr><tr><td style="text-align:right"><STRONG>.:</STRONG></td><td></td></tr><tr><td style="text-align:right"><STRONG>.:</STRONG></td><td>UV400</td></tr><tr><td style="text-align:right"><STRONG>Cam Rengi.:</STRONG></td><td>KAHVERENGİ</td></tr><tr><td style="text-align:right"><STRONG>.:</STRONG></td><td>SİYAH</td></tr></table><p>&nbsp;</p><p><img src="http://ae01.alicdn.com/kf/Ha47df332a90249889675c8c6935f06aci.jpg" alt="BrandLogo" width="300px"  /></p><p>&nbsp;</p><p><img src="http://ae01.alicdn.com/kf/H2553deefe571447f873731e767470f208.jpg" alt="BrandImage1" width="300px"  /></p>]]></Description>
		<Image1>https://markamilla.com/image/data/resimler/web-w-0208-34g-unisex-gunes-gozlugu-185842.jpg</Image1>
		<Image2>https://markamilla.com/image/data/resimler/web-w-0208-34g-unisex-gunes-gozlugu-185843.jpg</Image2>
		<Image3>https://markamilla.com/image/data/resimler/web-w-0208-34g-unisex-gunes-gozlugu-185844.jpg</Image3>
		<Image4>https://markamilla.com/image/data/ekartman/59-16-145.jpg</Image4>
			<Brand>Web</Brand>
			<Model>W 0208 34G</Model>
			<Volume>1</Volume>
	</Product>
</Products>
